LICENSE.txt
MANIFEST.in
NEWS.rst
README.rst
setup.py
django_stackato/__init__.py
django_stackato.egg-info/PKG-INFO
django_stackato.egg-info/SOURCES.txt
django_stackato.egg-info/dependency_links.txt
django_stackato.egg-info/top_level.txt
django_stackato/management/__init__.py
django_stackato/management/commands/__init__.py
django_stackato/management/commands/changepassword2.py