Metadata-Version: 1.0
Name: django-stackato
Version: 1.0
Summary: Django Stackato Extensions -- non-interactive changepassword
Home-page: http://github.com/ActiveState/django-stackato
Author: Sridhar Ratnakumar
Author-email: sridharr@activestate.com
License: MIT
Keywords: stackato django activestate
Platform: UNKNOWN
Classifier: Intended Audience :: Developers
Classifier: License :: OSI Approved :: MIT License
Classifier: Operating System :: OS Independent
Classifier: Programming Language :: Python :: 2.6
Classifier: Programming Language :: Python :: 2.7
Classifier: Topic :: Software Development :: Libraries :: Python Modules
Classifier: Topic :: Utilities
